misspy_core_fast/__init__.py
misspy_core_fast/exception.py
misspy_core_fast/http.py
misspy_core_fast/ws.py
misspy_core_fast-1.0.0.dist-info/LICENSE
misspy_core_fast-1.0.0.dist-info/METADATA
misspy_core_fast-1.0.0.dist-info/WHEEL
misspy_core_fast-1.0.0.dist-info/RECORD
